views_query_planning/__init__.py
views_query_planning/cli.py
views_query_planning/composer.py
views_query_planning/definitions.py
views_query_planning/exceptions.py
views_query_planning/query_planning.py
views_query_planning-1.3.1.dist-info/entry_points.txt
views_query_planning-1.3.1.dist-info/LICENSE
views_query_planning-1.3.1.dist-info/WHEEL
views_query_planning-1.3.1.dist-info/METADATA
views_query_planning-1.3.1.dist-info/RECORD
